python_actr/__init__.py
python_actr/logger.py
python_actr/model.py
python_actr/pattern.py
python_actr/production.py
python_actr/runner.py
python_actr/scheduler.py
python_actr/version.py
python_actr/actr/__init__.py
python_actr/actr/buffer.py
python_actr/actr/compile.py
python_actr/actr/core.py
python_actr/actr/dm.py
python_actr/actr/imaginal.py
python_actr/actr/motor.py
python_actr/actr/pm.py
python_actr/actr/sosvision.py
python_actr/actr/text.py
python_actr/actr/timer.py
python_actr/actr/vision.py
python_actr/display/__init__.py
python_actr/ui/__init__.py
python_actr/ui/htmltrace.py
python_actr/ui/pytag.py
python_actr-1.9.1.dist-info/LICENSE
python_actr-1.9.1.dist-info/METADATA
python_actr-1.9.1.dist-info/WHEEL
python_actr-1.9.1.dist-info/top_level.txt
python_actr-1.9.1.dist-info/RECORD
